pywps/__init__.py
pywps/configuration.py
pywps/dblog.py
pywps/dependencies.py
pywps/exceptions.py
pywps/ext_autodoc.py
pywps/tests.py
pywps/translations.py
pywps/util.py
pywps/app/Common.py
pywps/app/Process.py
pywps/app/Service.py
pywps/app/WPSRequest.py
pywps/app/__init__.py
pywps/app/basic.py
pywps/app/exceptions.py
pywps/inout/__init__.py
pywps/inout/array_encode.py
pywps/inout/basic.py
pywps/inout/inputs.py
pywps/inout/literaltypes.py
pywps/inout/outputs.py
pywps/inout/types.py
pywps/inout/formats/__init__.py
pywps/inout/storage/__init__.py
pywps/inout/storage/builder.py
pywps/inout/storage/file.py
pywps/inout/storage/implementationbuilder.py
pywps/inout/storage/s3.py
pywps/processing/__init__.py
pywps/processing/basic.py
pywps/processing/job.py
pywps/processing/scheduler.py
pywps/resources/__init__.py
pywps/resources/schemas/__init__.py
pywps/resources/schemas/wps_all.xsd
pywps/response/__init__.py
pywps/response/capabilities.py
pywps/response/describe.py
pywps/response/execute.py
pywps/response/status.py
pywps/schemas/geojson/README
pywps/schemas/geojson/bbox.json
pywps/schemas/geojson/crs.json
pywps/schemas/geojson/geojson.json
pywps/schemas/geojson/geometry.json
pywps/schemas/metalink/3.0/metalink.xsd
pywps/schemas/metalink/4.0/metalink4.xsd
pywps/schemas/metalink/4.0/xml.xsd
pywps/schemas/ncml/2.2/ncml-2.2.xsd
pywps/templates/1.0.0/capabilities/main.xml
pywps/templates/1.0.0/describe/bbox.xml
pywps/templates/1.0.0/describe/complex.xml
pywps/templates/1.0.0/describe/literal.xml
pywps/templates/1.0.0/describe/main.xml
pywps/templates/1.0.0/execute/main.xml
pywps/templates/2.0.0/capabilities/main.xml
pywps/templates/metalink/3.0/main.xml
pywps/templates/metalink/4.0/main.xml
pywps/validator/__init__.py
pywps/validator/allowed_value.py
pywps/validator/base.py
pywps/validator/complexvalidator.py
pywps/validator/literalvalidator.py
pywps/validator/mode.py
pywps_json-4.4.3.15.dist-info/LICENSE.txt
pywps_json-4.4.3.15.dist-info/METADATA
pywps_json-4.4.3.15.dist-info/WHEEL
pywps_json-4.4.3.15.dist-info/entry_points.txt
pywps_json-4.4.3.15.dist-info/top_level.txt
pywps_json-4.4.3.15.dist-info/RECORD
