Metadata-Version: 2.1
Name: pywps-json
Version: 4.4.3.15
Summary: PyWPS is an implementation of the Web Processing Service standard from the Open Geospatial Consortium. PyWPS is written in Python.
Home-page: https://pywps.org
Author: Jachym Cepicky
Author-email: jachym.cepicky@gmail.com
Maintainer: Idan Miara
Maintainer-email: idan@miara.com
License: MIT
Download-URL: https://github.com/geopython/pywps
Keywords: PyWPS WPS OGC processing
Platform: all
Classifier: Development Status :: 5 - Production/Stable
Classifier: Environment :: Web Environment
Classifier: Intended Audience :: Developers
Classifier: Intended Audience :: Science/Research
Classifier: License :: OSI Approved :: MIT License
Classifier: Operating System :: OS Independent
Classifier: Programming Language :: Python
Classifier: Programming Language :: Python :: 3
Classifier: Programming Language :: Python :: 3.6
Classifier: Programming Language :: Python :: 3.7
Classifier: Topic :: Scientific/Engineering :: GIS
Requires-Python: >=3.6, <4
License-File: LICENSE.txt
Requires-Dist: jinja2
Requires-Dist: jsonschema
Requires-Dist: lxml
Requires-Dist: owslib
Requires-Dist: python-dateutil
Requires-Dist: requests
Requires-Dist: SQLAlchemy
Requires-Dist: werkzeug
Requires-Dist: humanize
